gl_webhooks/__init__.py
gl_webhooks/__main__.py
gl_webhooks/api/metrics.py
gl_webhooks/api/metrics.yml
gl_webhooks/api/openapi.yml
gl_webhooks/api/x-responses.yml
gl_webhooks/api/badges/static.py
gl_webhooks/api/badges/static.yml
gl_webhooks/api/webhooks/gitlab/jobs/monitor.py
gl_webhooks/api/webhooks/gitlab/jobs/monitor.yml
gl_webhooks/clients/gitlab.py
gl_webhooks/controllers/jobs_monitor.py
gl_webhooks/models/__init__.py
gl_webhooks/models/badges.py
gl_webhooks/tasks/jobs_monitor.py
gl_webhooks-1.1.17.dist-info/LICENSE
gl_webhooks-1.1.17.dist-info/METADATA
gl_webhooks-1.1.17.dist-info/WHEEL
gl_webhooks-1.1.17.dist-info/entry_points.txt
gl_webhooks-1.1.17.dist-info/top_level.txt
gl_webhooks-1.1.17.dist-info/zip-safe
gl_webhooks-1.1.17.dist-info/RECORD
