Metadata-Version: 2.1
Name: gl-webhooks
Version: 1.1.17
Summary: GL Webhooks is a project that provides GitLab functionalities via webhook endpoints.
Author-email: Julien Lecomte <julien@lecomte.at>
License: MIT
Project-URL: Homepage, https://gitlab.com/jlecomte/python/gl-webhooks
Project-URL: Documentation, https://jlecomte.gitlab.io/python/gl-webhooks/
Project-URL: Source code, https://gitlab.com/jlecomte/python/gl-webhooks
Project-URL: Bug tracker, https://gitlab.com/jlecomte/python/gl-webhooks/-/issues
Classifier: License :: OSI Approved :: MIT License
Classifier: Intended Audience :: Developers
Classifier: Development Status :: 3 - Alpha
Classifier: Programming Language :: Python :: 3 :: Only
Classifier: Programming Language :: Python :: 3.9
Requires-Python: >=3.9
License-File: LICENSE
Requires-Dist: celery[redis]
Requires-Dist: filelock
Requires-Dist: flasket-gitlab (>=0.2.0)
Requires-Dist: gitlab-scripts
